ardupilot_methodic_configurator/ArduPilot_icon.png
ardupilot_methodic_configurator/ArduPilot_logo.png
ardupilot_methodic_configurator/__init__.py
ardupilot_methodic_configurator/__main__.py
ardupilot_methodic_configurator/annotate_params.py
ardupilot_methodic_configurator/argparse_check_range.py
ardupilot_methodic_configurator/backend_filesystem.py
ardupilot_methodic_configurator/backend_filesystem_configuration_steps.py
ardupilot_methodic_configurator/backend_filesystem_program_settings.py
ardupilot_methodic_configurator/backend_filesystem_vehicle_components.py
ardupilot_methodic_configurator/backend_flightcontroller.py
ardupilot_methodic_configurator/backend_flightcontroller_info.py
ardupilot_methodic_configurator/backend_mavftp.py
ardupilot_methodic_configurator/battery_cell_voltages.py
ardupilot_methodic_configurator/common_arguments.py
ardupilot_methodic_configurator/configuration_steps_ArduCopter.json
ardupilot_methodic_configurator/configuration_steps_ArduPlane.json
ardupilot_methodic_configurator/configuration_steps_Heli.json
ardupilot_methodic_configurator/configuration_steps_Rover.json
ardupilot_methodic_configurator/extract_param_defaults.py
ardupilot_methodic_configurator/frontend_tkinter_base.py
ardupilot_methodic_configurator/frontend_tkinter_component_editor.py
ardupilot_methodic_configurator/frontend_tkinter_component_editor_base.py
ardupilot_methodic_configurator/frontend_tkinter_connection_selection.py
ardupilot_methodic_configurator/frontend_tkinter_directory_selection.py
ardupilot_methodic_configurator/frontend_tkinter_entry_dynamic.py
ardupilot_methodic_configurator/frontend_tkinter_flightcontroller_info.py
ardupilot_methodic_configurator/frontend_tkinter_pair_tuple_combobox.py
ardupilot_methodic_configurator/frontend_tkinter_parameter_editor.py
ardupilot_methodic_configurator/frontend_tkinter_parameter_editor_documentation_frame.py
ardupilot_methodic_configurator/frontend_tkinter_parameter_editor_table.py
ardupilot_methodic_configurator-1.0.8.dist-info/LICENSE.md
ardupilot_methodic_configurator-1.0.8.dist-info/METADATA
ardupilot_methodic_configurator-1.0.8.dist-info/WHEEL
ardupilot_methodic_configurator-1.0.8.dist-info/entry_points.txt
ardupilot_methodic_configurator-1.0.8.dist-info/top_level.txt
ardupilot_methodic_configurator-1.0.8.dist-info/RECORD
