Metadata-Version: 2.2
Name: ardupilot_methodic_configurator
Version: 1.0.8
Summary: A clear configuration sequence for ArduPilot vehicles
Author-email: Amilcar do Carmo Lucas <amilcar.lucas@iav.de>
Maintainer-email: Amilcar do Carmo Lucas <amilcar.lucas@iav.de>
License: GPLv3
Project-URL: homepage, https://github.com/ArduPilot/MethodicConfigurator
Project-URL: documentation, https://github.com/ArduPilot/MethodicConfigurator/blob/master/USERMANUAL.md
Project-URL: issues, https://github.com/ArduPilot/MethodicConfigurator/issues
Project-URL: source, https://github.com/ArduPilot/MethodicConfigurator
Project-URL: forum, https://discuss.ardupilot.org/t/new-ardupilot-methodic-configurator-gui/115038/
Project-URL: chat, https://discord.com/invite/ArduPilot
Project-URL: download, https://github.com/ArduPilot/MethodicConfigurator/releases
Project-URL: changelog, https://github.com/ArduPilot/MethodicConfigurator/releases
Keywords: ArduPilot,Configuration,SCM,Methodic,ArduCopter,ArduPlane,ArduRover,ArduSub
Classifier: Development Status :: 5 - Production/Stable
Classifier: Intended Audience :: Developers
Classifier: Intended Audience :: Education
Classifier: Intended Audience :: End Users/Desktop
Classifier: Intended Audience :: Manufacturing
Classifier: Intended Audience :: Science/Research
Classifier: License :: OSI Approved :: GNU General Public License v3 (GPLv3)
Classifier: Natural Language :: English
Classifier: Natural Language :: Chinese (Simplified)
Classifier: Natural Language :: German
Classifier: Natural Language :: Portuguese
Classifier: Operating System :: OS Independent
Classifier: Programming Language :: Python :: 3.9
Classifier: Programming Language :: Python :: 3.10
Classifier: Programming Language :: Python :: 3.11
Classifier: Programming Language :: Python :: 3.12
Classifier: Programming Language :: Python :: 3.13
Classifier: Topic :: Software Development :: Embedded Systems
Classifier: Topic :: System :: Installation/Setup
Classifier: Topic :: Scientific/Engineering
Requires-Python: >=3.9
License-File: LICENSE.md
Requires-Dist: defusedxml
Requires-Dist: matplotlib
Requires-Dist: numpy
Requires-Dist: platformdirs
Requires-Dist: pymavlink
Requires-Dist: pyserial
Requires-Dist: pillow
Requires-Dist: setuptools
Requires-Dist: requests
Provides-Extra: dev
Requires-Dist: ruff; extra == "dev"
Requires-Dist: pre-commit; extra == "dev"
Requires-Dist: pytest; extra == "dev"
Requires-Dist: pytest-cov; extra == "dev"
Requires-Dist: coverage; extra == "dev"
Requires-Dist: mock; extra == "dev"
Requires-Dist: pyinstaller; extra == "dev"
Requires-Dist: mypy; extra == "dev"
Requires-Dist: pyright; extra == "dev"
Requires-Dist: github; extra == "dev"
